cnet/__about__.py
cnet/__init__.py
cnet/algorithms/__init__.py
cnet/algorithms/diffusion.py
cnet/algorithms/shortest_path.py
cnet/algorithms/traffic_assignment.py
cnet/classes/__init__.py
cnet/classes/network.py
cnet/classes/paths.py
cnet/classes/road_network.py
cnet/classes/spatial_network.py
cnet/utils/__init__.py
cnet/utils/config.py
cnet/utils/exceptions.py
cnet/utils/helpers.py
cnet/utils/logger.py
cnet/visualization/__init__.py
cnet/visualization/canvas.py
cnet/visualization/drawing.py
cnet/visualization/plot.py
cnet/visualization/units.py
cnet-0.0.1.dist-info/METADATA
cnet-0.0.1.dist-info/RECORD
cnet-0.0.1.dist-info/WHEEL
cnet-0.0.1.dist-info/top_level.txt
