Metadata-Version: 2.1
Name: cnet
Version: 0.0.1
Summary: Another Complex Network module for Python!
Home-page: https://github.com/hackl/cnet
Author: Juergen Hackl
Author-email: hackl.j@gmx.at
License: License :: OSI Approved :: GNU General Public License v3 (GPLv3)
Download-URL: https://pypi.org/project/cnet
Platform: UNKNOWN
Classifier: Development Status :: 2 - Pre-Alpha
Classifier: License :: OSI Approved :: GNU General Public License v3 (GPLv3)
Classifier: Operating System :: OS Independent
Classifier: Programming Language :: Python
Classifier: Programming Language :: Python :: 3
Classifier: Intended Audience :: Science/Research
Classifier: Topic :: Scientific/Engineering :: Mathematics
Classifier: Topic :: Scientific/Engineering :: Physics
Requires-Dist: numpy
Requires-Dist: scipy
